natquiz/__init__.py
natquiz/app.py
natquiz/parse_questions.py
natquiz/questions.toml
natquiz-0.3.0.dist-info/LICENSE
natquiz-0.3.0.dist-info/METADATA
natquiz-0.3.0.dist-info/WHEEL
natquiz-0.3.0.dist-info/entry_points.txt
natquiz-0.3.0.dist-info/top_level.txt
natquiz-0.3.0.dist-info/RECORD
