Metadata-Version: 2.1
Name: natquiz
Version: 0.3.0
Summary: A command line tool to help people prepare for their US naturalization test.
Author-email: Carlos Paniagua <cpaniaguam@gmail.com>
License: MIT License
Project-URL: Homepage, https://github.com/cpaniaguam/natquiz
Project-URL: Bug Reports, https://github.com/cpaniaguam/natquiz/issues
Project-URL: Source, https://github.com/cpaniaguam/natquiz
Keywords: command line tool,US naturalization
Classifier: Development Status :: 3 - Alpha
Classifier: Intended Audience :: Education
Classifier: Intended Audience :: End Users/Desktop
Classifier: Topic :: Education
Classifier: Programming Language :: Python :: 3.11
Classifier: Programming Language :: Python :: 3 :: Only
Requires-Python: >=3.11
License-File: LICENSE
